cgnal/core/__init__.py
cgnal/core/_version.py
cgnal/core/py.typed
cgnal/core/config/__init__.py
cgnal/core/data/__init__.py
cgnal/core/data/exceptions.py
cgnal/core/data/layer/__init__.py
cgnal/core/data/layer/mongo/__init__.py
cgnal/core/data/layer/mongo/archivers.py
cgnal/core/data/layer/mongo/dao.py
cgnal/core/data/layer/pandas/__init__.py
cgnal/core/data/layer/pandas/archivers.py
cgnal/core/data/layer/pandas/dao.py
cgnal/core/data/layer/pandas/databases.py
cgnal/core/data/model/__init__.py
cgnal/core/data/model/core.py
cgnal/core/data/model/ml.py
cgnal/core/data/model/text.py
cgnal/core/logging/__init__.py
cgnal/core/logging/defaults.py
cgnal/core/tests/__init__.py
cgnal/core/tests/core.py
cgnal/core/typing/__init__.py
cgnal/core/utils/__init__.py
cgnal/core/utils/cloud.py
cgnal/core/utils/decorators.py
cgnal/core/utils/dict.py
cgnal/core/utils/email.py
cgnal/core/utils/fs.py
cgnal/core/utils/pandas.py
requirements/requirements.in
cgnal_core-2.0.2.dist-info/LICENSE
cgnal_core-2.0.2.dist-info/METADATA
cgnal_core-2.0.2.dist-info/WHEEL
cgnal_core-2.0.2.dist-info/top_level.txt
cgnal_core-2.0.2.dist-info/RECORD
