Metadata-Version: 2.1
Name: cgnal-core
Version: 2.0.2
Summary: A Python library of data structures optimized for machine learning tasks
Home-page: https://github.com/CGnal/cgnal-core
Author: CGnal s.r.l.
Author-email: info@cgnal.com
License: MIT
Platform: UNKNOWN
Classifier: Programming Language :: Python :: 3
Classifier: License :: OSI Approved :: MIT License
Classifier: Operating System :: OS Independent
Requires-Python: ~=3.7
Requires-Dist: cfg-load (>=0.8)
Requires-Dist: deprecated (>=1.2.12)
Requires-Dist: dill (>=0.3)
Requires-Dist: pandas (>=1.0)
Requires-Dist: pymongo (>=4.0)
Requires-Dist: scipy (>=1.7.3)
Requires-Dist: setuptools (>=47.1)
Requires-Dist: typeguard (>=2.13.0)
Requires-Dist: typing-extensions (>=4.0)
